{
  "turkey_istanbul_BkeemJXg": {
    "youtube_id": "D_4J_Sb0d0E",
    "youtube_url": "https://www.youtube.com/watch?v=D_4J_Sb0d0E",
    "page": "posts/turkey/istanbul.html"
  },
  "turkey_istanbul_UmdnM7nJ": {
    "youtube_id": "1yh4iH6oGRk",
    "youtube_url": "https://www.youtube.com/watch?v=1yh4iH6oGRk",
    "page": "posts/turkey/istanbul.html"
  },
  "turkey_istanbul_f8x2yNIM": {
    "youtube_id": "HS1Ne2x_57Q",
    "youtube_url": "https://www.youtube.com/watch?v=HS1Ne2x_57Q",
    "page": "posts/turkey/istanbul.html"
  },
  "turkey_istanbul_zg79qVYS": {
    "youtube_id": "XFBSnjbpFew",
    "youtube_url": "https://www.youtube.com/watch?v=XFBSnjbpFew",
    "page": "posts/turkey/istanbul.html"
  },
  "turkey_istanbul_24kIwoKr": {
    "youtube_id": "R2yMsVYaos0",
    "youtube_url": "https://www.youtube.com/watch?v=R2yMsVYaos0",
    "page": "posts/turkey/istanbul.html"
  },
  "turkey_cappadocia_VnPFrcH5": {
    "youtube_id": "CnVZqj_-b0k",
    "youtube_url": "https://www.youtube.com/watch?v=CnVZqj_-b0k",
    "page": "posts/turkey/cappadocia.html"
  },
  "turkey_cappadocia_0Kg85ghi": {
    "youtube_id": "Sa6jk3wZBKk",
    "youtube_url": "https://www.youtube.com/watch?v=Sa6jk3wZBKk",
    "page": "posts/turkey/cappadocia.html"
  },
  "turkey_antalya_7DL3lCr6": {
    "youtube_id": "mrAX3dRgy6Q",
    "youtube_url": "https://www.youtube.com/watch?v=mrAX3dRgy6Q",
    "page": "posts/turkey/antalya.html"
  },
  "turkey_antalya_VSmaHLjj": {
    "youtube_id": "Bq4MdF-Cnr8",
    "youtube_url": "https://www.youtube.com/watch?v=Bq4MdF-Cnr8",
    "page": "posts/turkey/antalya.html"
  },
  "turkey_antalya_xkdJyY4G": {
    "youtube_id": "8Z71lc2bjUs",
    "youtube_url": "https://www.youtube.com/watch?v=8Z71lc2bjUs",
    "page": "posts/turkey/antalya.html"
  },
  "turkey_sanliurfa_A7HCL10l": {
    "youtube_id": "i-3sYhE-uic",
    "youtube_url": "https://www.youtube.com/watch?v=i-3sYhE-uic",
    "page": "posts/turkey/sanliurfa.html"
  }
}